src/rmlst_api/__init__.py
src/rmlst_api/cli.py
src/rmlst_api/constants.py
src/rmlst_api/rmlst.py
rmlst_api-0.1.8.dist-info/LICENSE
rmlst_api-0.1.8.dist-info/METADATA
rmlst_api-0.1.8.dist-info/WHEEL
rmlst_api-0.1.8.dist-info/entry_points.txt
rmlst_api-0.1.8.dist-info/RECORD
