Metadata-Version: 2.3
Name: rmlst-api
Version: 0.1.8
Summary: Python package to perform rMLST through the PubMLST API
License: MIT
Author: Domenico Simone
Author-email: dome.simone@gmail.com
Requires-Python: >3.8
Classifier: License :: OSI Approved :: MIT License
Classifier: Programming Language :: Python :: 3
Classifier: Programming Language :: Python :: 3.9
Classifier: Programming Language :: Python :: 3.10
Classifier: Programming Language :: Python :: 3.11
Classifier: Programming Language :: Python :: 3.12
Classifier: Programming Language :: Python :: 3.13
Requires-Dist: click (>=8.1.8,<9.0.0)
Requires-Dist: requests (>=2.32.3,<3.0.0)
Project-URL: Bug Tracker, https://github.com/domenico-simone/rmlst_api/issues
Project-URL: Homepage, https://github.com/domenico-simone/rmlst_api
